calculation123/__init__.py
calculation123/calculator.py
calculation123-2.1.0.dist-info/LICENSE
calculation123-2.1.0.dist-info/METADATA
calculation123-2.1.0.dist-info/WHEEL
calculation123-2.1.0.dist-info/top_level.txt
calculation123-2.1.0.dist-info/RECORD
